video_processor/__init__.py
video_processor/config.py
video_processor/constants.py
video_processor/exceptions.py
video_processor/ai/__init__.py
video_processor/ai/audio_extractor.py
video_processor/ai/content_analyzer.py
video_processor/ai/content_analyzer_original.py
video_processor/ai/models.py
video_processor/ai/motion_detector.py
video_processor/ai/msprites2_adapter.py
video_processor/ai/ollama_client.py
video_processor/ai/quality_assessor.py
video_processor/ai/scene_analyzer.py
video_processor/ai/transcript_writer.py
video_processor/ai/video_360_analyzer.py
video_processor/ai/video_transcriber.py
video_processor/ai/whisper_client.py
video_processor/core/__init__.py
video_processor/core/advanced_encoders.py
video_processor/core/av1_encoder.py
video_processor/core/codec_capabilities.py
video_processor/core/encoders.py
video_processor/core/enhanced_processor.py
video_processor/core/hdr_processor.py
video_processor/core/hevc_encoder.py
video_processor/core/metadata.py
video_processor/core/processor.py
video_processor/core/thumbnails.py
video_processor/core/thumbnails_360.py
video_processor/core/thumbnail_360/__init__.py
video_processor/core/thumbnail_360/frame_extractor.py
video_processor/core/thumbnail_360/projection_processor.py
video_processor/core/thumbnail_360/sprite_generator.py
video_processor/core/thumbnail_360/thumbnail_orchestrator.py
video_processor/storage/__init__.py
video_processor/storage/backends.py
video_processor/streaming/__init__.py
video_processor/streaming/adaptive.py
video_processor/streaming/adaptive_orchestrator.py
video_processor/streaming/bitrate_manager.py
video_processor/streaming/dash.py
video_processor/streaming/hls.py
video_processor/streaming/models.py
video_processor/streaming/playlist_generator.py
video_processor/tasks/__init__.py
video_processor/tasks/compat.py
video_processor/tasks/migration.py
video_processor/tasks/procrastinate_tasks.py
video_processor/tasks/worker_compatibility.py
video_processor/utils/__init__.py
advanced_video_processor-0.6.0.dist-info/METADATA
advanced_video_processor-0.6.0.dist-info/WHEEL
advanced_video_processor-0.6.0.dist-info/licenses/LICENSE
advanced_video_processor-0.6.0.dist-info/RECORD
