Metadata-Version: 2.4
Name: advanced-video-processor
Version: 0.6.0
Summary: Professional video processing pipeline with computer vision analysis, 360° processing, adaptive streaming, and AI-powered transcription (msprites2)
Project-URL: Homepage, https://git.supported.systems/video/video-processor
Project-URL: Documentation, https://git.supported.systems/video/video-processor/tree/main/docs
Project-URL: Repository, https://git.supported.systems/video/video-processor.git
Project-URL: Issues, https://git.supported.systems/video/video-processor/issues
Author-email: Ryan Malloy <ryan@malloys.us>
License: MIT
License-File: LICENSE
Keywords: 360,computer-vision,ffmpeg,multimedia,opencv,processing,streaming,video,vr
Classifier: Development Status :: 4 - Beta
Classifier: Intended Audience :: Developers
Classifier: License :: OSI Approved :: MIT License
Classifier: Programming Language :: Python :: 3
Classifier: Programming Language :: Python :: 3.11
Classifier: Programming Language :: Python :: 3.12
Classifier: Topic :: Multimedia :: Video
Classifier: Topic :: Multimedia :: Video :: Conversion
Classifier: Topic :: Software Development :: Libraries :: Python Modules
Requires-Python: >=3.11
Requires-Dist: exifread>=3.5.1
Requires-Dist: ffmpeg-python>=0.2.0
Requires-Dist: msprites2[ai]>=0.13.0
Requires-Dist: pillow>=11.2.1
Requires-Dist: procrastinate<4.0.0,>=2.15.1
Requires-Dist: psycopg[pool]>=3.2.9
Requires-Dist: pydantic-settings>=2.0.0
Requires-Dist: pydantic>=2.0.0
Requires-Dist: python-dateutil>=2.9.0
Provides-Extra: all
Requires-Dist: librosa>=0.9.0; extra == 'all'
Requires-Dist: numpy>=1.21.0; extra == 'all'
Requires-Dist: opencv-python>=4.5.0; extra == 'all'
Requires-Dist: pillow>=9.0.0; extra == 'all'
Requires-Dist: py360convert>=0.1.0; extra == 'all'
Requires-Dist: scikit-learn>=1.0.0; extra == 'all'
Requires-Dist: scipy>=1.7.0; extra == 'all'
Requires-Dist: soundfile>=0.11.0; extra == 'all'
Provides-Extra: analysis
Requires-Dist: numpy>=1.21.0; extra == 'analysis'
Requires-Dist: opencv-python>=4.5.0; extra == 'analysis'
Requires-Dist: pillow>=9.0.0; extra == 'analysis'
Requires-Dist: scikit-learn>=1.0.0; extra == 'analysis'
Provides-Extra: dev
Requires-Dist: build>=1.0.0; extra == 'dev'
Requires-Dist: docker>=6.1.0; extra == 'dev'
Requires-Dist: mypy>=1.7.0; extra == 'dev'
Requires-Dist: psycopg2-binary>=2.9.0; extra == 'dev'
Requires-Dist: pytest-asyncio>=0.21.0; extra == 'dev'
Requires-Dist: pytest-cov>=4.0.0; extra == 'dev'
Requires-Dist: pytest>=7.0.0; extra == 'dev'
Requires-Dist: ruff>=0.1.0; extra == 'dev'
Requires-Dist: twine>=5.0.0; extra == 'dev'
Provides-Extra: metadata-360
Requires-Dist: exifread>=3.0.0; extra == 'metadata-360'
Provides-Extra: opencv
Requires-Dist: numpy>=1.21.0; extra == 'opencv'
Requires-Dist: opencv-python>=4.5.0; extra == 'opencv'
Requires-Dist: pillow>=9.0.0; extra == 'opencv'
Provides-Extra: spatial-audio
Requires-Dist: librosa>=0.9.0; extra == 'spatial-audio'
Requires-Dist: soundfile>=0.11.0; extra == 'spatial-audio'
Provides-Extra: video-360
Requires-Dist: numpy>=1.21.0; extra == 'video-360'
Requires-Dist: opencv-python>=4.5.0; extra == 'video-360'
Requires-Dist: pillow>=9.0.0; extra == 'video-360'
Requires-Dist: py360convert>=0.1.0; extra == 'video-360'
Requires-Dist: scipy>=1.7.0; extra == 'video-360'
Provides-Extra: video-360-full
Requires-Dist: librosa>=0.9.0; extra == 'video-360-full'
Requires-Dist: numpy>=1.21.0; extra == 'video-360-full'
Requires-Dist: opencv-python>=4.5.0; extra == 'video-360-full'
Requires-Dist: pillow>=9.0.0; extra == 'video-360-full'
Requires-Dist: py360convert>=0.1.0; extra == 'video-360-full'
Requires-Dist: scikit-learn>=1.0.0; extra == 'video-360-full'
Requires-Dist: scipy>=1.7.0; extra == 'video-360-full'
Requires-Dist: soundfile>=0.11.0; extra == 'video-360-full'
